mpl_smithchart/__init__.py
mpl_smithchart/_version.py
mpl_smithchart/smithaxes.py
mpl_smithchart/smithhelper.py
mpl_smithchart-0.1.2.dist-info/COPYING
mpl_smithchart-0.1.2.dist-info/METADATA
mpl_smithchart-0.1.2.dist-info/WHEEL
mpl_smithchart-0.1.2.dist-info/top_level.txt
mpl_smithchart-0.1.2.dist-info/RECORD
