Metadata-Version: 2.1
Name: mpl-smithchart
Version: 0.1.2
Summary: An extension for matplotlib providing a projection class to generate high quality Smith Chart plots.
Author-email: Paul Staerke <paul.staerke@gmail.com>, Spencer Chang <spencer@sycee.xyz>
License: BSD
Project-URL: repository, https://github.com/schang412/mpl-smithchart
Requires-Python: >=3.8
License-File: COPYING
Requires-Dist: matplotlib (>=1.2)
Requires-Dist: numpy (>=1.24.3)
Requires-Dist: scipy (>=1.9.3)
